convertable_model/__init__.py
convertable_model/admin.py
convertable_model/apps.py
convertable_model/json_model.py
convertable_model/models.py
convertable_model/tests.py
convertable_model/views.py
convertable_model/migrations/0001_initial.py
convertable_model/migrations/__init__.py
django_json_convertible_models-0.1.1.dist-info/LICENSE
django_json_convertible_models-0.1.1.dist-info/METADATA
django_json_convertible_models-0.1.1.dist-info/WHEEL
django_json_convertible_models-0.1.1.dist-info/top_level.txt
django_json_convertible_models-0.1.1.dist-info/RECORD
